pullover-1.1.1.dist-info/DESCRIPTION.rst
pullover-1.1.1.dist-info/METADATA
pullover-1.1.1.dist-info/metadata.json
pullover-1.1.1.dist-info/entry_points.txt
pullover-1.1.1.dist-info/top_level.txt
pullover-1.1.1.dist-info/zip-safe
pullover-1.1.1.dist-info/WHEEL
pullover-1.1.1.dist-info/RECORD
pullover/exceptions.py
pullover/user.py
pullover/message.py
pullover/__init__.py
pullover/util.py
pullover/application.py
pullover/__main__.py
pullover/tests/test_util.py
pullover/tests/__init__.py
pullover/tests/test_main.py
pullover/tests/test_init.py
pullover/tests/test_application.py
pullover/tests/test_message.py
pullover/tests/test_user.py
