Metadata-Version: 2.0
Name: pullover
Version: 1.1.1
Summary: The simplest Pushover API wrapper for Python.
Home-page: https://github.com/gebn/pullover
Author: George Brighton
Author-email: oss@gebn.co.uk
License: MIT
Platform: UNKNOWN
Classifier: Development Status :: 5 - Production/Stable
Classifier: Environment :: Console
Classifier: Intended Audience :: Developers
Classifier: License :: OSI Approved :: MIT License
Classifier: Operating System :: OS Independent
Classifier: Programming Language :: Python
Classifier: Programming Language :: Python :: 2
Classifier: Programming Language :: Python :: 2.7
Classifier: Programming Language :: Python :: 3
Classifier: Programming Language :: Python :: 3.3
Classifier: Programming Language :: Python :: 3.4
Classifier: Programming Language :: Python :: 3.5
Classifier: Programming Language :: Python :: 3.6
Classifier: Programming Language :: Python :: 3.7
Classifier: Topic :: Software Development :: Libraries :: Python Modules
Requires-Dist: backoff
Requires-Dist: requests
Requires-Dist: python-dateutil
Requires-Dist: pytz
Requires-Dist: six (>=1.9.0)
